crawapi/__init__.py
crawlutils/__init__.py
crawlutils/date_utils.py
crawlutils/log.py
crawlutils/num_utils.py
crawlutils/soup_traversal.py
crawlutils/text_utils.py
crawler_commons-0.0.54.dist-info/LICENSE
crawler_commons-0.0.54.dist-info/METADATA
crawler_commons-0.0.54.dist-info/WHEEL
crawler_commons-0.0.54.dist-info/top_level.txt
crawler_commons-0.0.54.dist-info/RECORD
