Metadata-Version: 2.1
Name: crawler-commons
Version: 0.0.54
Summary: crawler commons
Home-page: https://github.com/cheddars/crawler_commons
Author: cheddars
Author-email: nezahrish@gmail.com
License: MIT
Classifier: Programming Language :: Python :: 3
Classifier: License :: OSI Approved :: MIT License
Classifier: Operating System :: OS Independent
License-File: LICENSE
Requires-Dist: requests
Requires-Dist: numpy
Requires-Dist: pyyaml
